[{"userId":"1","firstName":"Alden","lastName":"Humerstone","email":"ahumerstone0@nationalgeographic.com","location":"Dabou","isActive":true,"zcmRole":" ","admRole":"vivamus","lastUpdated":"7/17/2023","updateUser":"ahumerstone0","comsId":"ahumerstone0"},
{"userId":"2","firstName":"Pierre","lastName":"Mears","email":"pmears1@artisteer.com","location":"Moryń","isActive":true,"zcmRole":" ","admRole":"pharetra","lastUpdated":"9/29/2022","updateUser":"pmears1","comsId":"pmears1"},
{"userId":"3","firstName":"Heddie","lastName":"Artharg","email":"hartharg2@drupal.org","location":"E’zhou","isActive":false,"zcmRole":" ","admRole":"morbi","lastUpdated":"8/29/2022","updateUser":"hartharg2","comsId":"hartharg2"},
{"userId":"4","firstName":"Quintina","lastName":"Claringbold","email":"qclaringbold3@cnbc.com","location":"Klášter","isActive":false,"zcmRole":" ","admRole":"mus","lastUpdated":"7/15/2023","updateUser":"qclaringbold3","comsId":"qclaringbold3"},
{"userId":"5","firstName":"Abbie","lastName":"Leckenby","email":"aleckenby4@thetimes.co.uk","location":"Blerim","isActive":false,"zcmRole":" ","admRole":"mauris","lastUpdated":"10/7/2022","updateUser":"aleckenby4","comsId":"aleckenby4"},
{"userId":"6","firstName":"Rabi","lastName":"Hudd","email":"rhudd5@themeforest.net","location":"La Chapelle-sur-Erdre","isActive":false,"zcmRole":" ","admRole":"donec","lastUpdated":"11/29/2022","updateUser":"rhudd5","comsId":"rhudd5"},
{"userId":"7","firstName":"Terencio","lastName":"Geraldo","email":"tgeraldo6@howstuffworks.com","location":"Herrera","isActive":true,"zcmRole":" ","admRole":"ut","lastUpdated":"7/19/2023","updateUser":"tgeraldo6","comsId":"tgeraldo6"},
{"userId":"8","firstName":"Hubert","lastName":"Albisser","email":"halbisser7@dell.com","location":"Rungis","isActive":false,"zcmRole":" ","admRole":"massa","lastUpdated":"3/30/2023","updateUser":"halbisser7","comsId":"halbisser7"},
{"userId":"9","firstName":"Lemuel","lastName":"Malsher","email":"lmalsher8@wired.com","location":"Sambirata","isActive":false,"zcmRole":" ","admRole":"ante","lastUpdated":"4/3/2023","updateUser":"lmalsher8","comsId":"lmalsher8"},
{"userId":"10","firstName":"Stormi","lastName":"Joslow","email":"sjoslow9@posterous.com","location":"The Valley","isActive":false,"zcmRole":" ","admRole":"cubilia","lastUpdated":"7/6/2023","updateUser":"sjoslow9","comsId":"sjoslow9"},
{"userId":"11","firstName":"Sigismundo","lastName":"Frostick","email":"sfrosticka@ed.gov","location":"Hetou","isActive":true,"zcmRole":" ","admRole":"quisque","lastUpdated":"1/19/2023","updateUser":"sfrosticka","comsId":"sfrosticka"},
{"userId":"12","firstName":"Pierson","lastName":"Manns","email":"pmannsb@patch.com","location":"Qiaotou","isActive":true,"zcmRole":" ","admRole":"elementum","lastUpdated":"4/26/2023","updateUser":"pmannsb","comsId":"pmannsb"},
{"userId":"13","firstName":"Stormi","lastName":"Hanhardt","email":"thanhardtc@tripadvisor.com","location":"Borovikha","isActive":false,"zcmRole":" ","admRole":"magna","lastUpdated":"2/19/2023","updateUser":"thanhardtc","comsId":"thanhardtc"},
{"userId":"14","firstName":"Lauren","lastName":"Rutherford","email":"lrutherfordd@shareasale.com","location":"Chichaoua","isActive":true,"zcmRole":" ","admRole":"consectetuer","lastUpdated":"12/1/2022","updateUser":"lrutherfordd","comsId":"lrutherfordd"},
{"userId":"15","firstName":"Shaine","lastName":"Skerrett","email":"sskerrette@youtube.com","location":"Borisovka","isActive":false,"zcmRole":" ","admRole":"eleifend","lastUpdated":"5/16/2023","updateUser":"sskerrette","comsId":"sskerrette"},
{"userId":"16","firstName":"Gerhard","lastName":"Veasey","email":"gveaseyf@reddit.com","location":"Bry-sur-Marne","isActive":false,"zcmRole":" ","admRole":"sollicitudin","lastUpdated":"7/21/2023","updateUser":"gveaseyf","comsId":"gveaseyf"},
{"userId":"17","firstName":"Jan","lastName":"Brigstock","email":"jbrigstockg@t-online.de","location":"Shuyuan","isActive":true,"zcmRole":" ","admRole":"maecenas","lastUpdated":"3/24/2023","updateUser":"jbrigstockg","comsId":"jbrigstockg"},
{"userId":"18","firstName":"Wyn","lastName":"Afield","email":"wafieldh@usnews.com","location":"Washington","isActive":false,"zcmRole":" ","admRole":"ante","lastUpdated":"1/8/2023","updateUser":"wafieldh","comsId":"wafieldh"},
{"userId":"19","firstName":"Gratiana","lastName":"Robbeke","email":"grobbekei@nhs.uk","location":"Trzebiatów","isActive":false,"zcmRole":" ","admRole":"quis","lastUpdated":"5/19/2023","updateUser":"grobbekei","comsId":"grobbekei"},
{"userId":"20","firstName":"Jakie","lastName":"Kalvin","email":"jkalvinj@utexas.edu","location":"Obigarm","isActive":true,"zcmRole":" ","admRole":"pede","lastUpdated":"7/9/2023","updateUser":"jkalvinj","comsId":"jkalvinj"},
{"userId":"21","firstName":"Berty","lastName":"Ogborne","email":"bogbornek@apple.com","location":"Mauloo","isActive":true,"zcmRole":"Subcontractor","admRole":"tristique","lastUpdated":"6/17/2023","updateUser":"bogbornek","comsId":"bogbornek"},
{"userId":"22","firstName":"Cortie","lastName":"Bodham","email":"cbodhaml@squidoo.com","location":"Pescara","isActive":true,"zcmRole":" ","admRole":"volutpat","lastUpdated":"2/15/2023","updateUser":"cbodhaml","comsId":"cbodhaml"},
{"userId":"23","firstName":"Linzy","lastName":"Gruczka","email":"lgruczkam@biblegateway.com","location":"São Félix do Xingu","isActive":false,"zcmRole":" ","admRole":"at","lastUpdated":"10/4/2022","updateUser":"lgruczkam","comsId":"lgruczkam"},
{"userId":"24","firstName":"Sam","lastName":"MacQuist","email":"smacquistn@youtu.be","location":"Tanalt","isActive":true,"zcmRole":" ","admRole":"in","lastUpdated":"10/14/2022","updateUser":"smacquistn","comsId":"smacquistn"},
{"userId":"25","firstName":"Haily","lastName":"Martinyuk","email":"hmartinyuko@clickbank.net","location":"Kladruby","isActive":true,"zcmRole":" ","admRole":"ut","lastUpdated":"5/31/2023","updateUser":"hmartinyuko","comsId":"hmartinyuko"},
{"userId":"26","firstName":"Otto","lastName":"Harkin","email":"oharkinp@webmd.com","location":"Druzhba","isActive":false,"zcmRole":" ","admRole":"turpis","lastUpdated":"11/16/2022","updateUser":"oharkinp","comsId":"oharkinp"},
{"userId":"27","firstName":"Colet","lastName":"Althrope","email":"calthropeq@skyrock.com","location":"Cekcyn","isActive":true,"zcmRole":" ","admRole":"felis","lastUpdated":"5/16/2023","updateUser":"calthropeq","comsId":"calthropeq"},
{"userId":"28","firstName":"Gasparo","lastName":"Lampbrecht","email":"glampbrechtr@blogs.com","location":"Pinellas Park","isActive":true,"zcmRole":" ","admRole":"diam","lastUpdated":"4/26/2023","updateUser":"glampbrechtr","comsId":"glampbrechtr"},
{"userId":"29","firstName":"Shela","lastName":"Kindleysides","email":"skindleysidess@npr.org","location":"Parse","isActive":false,"zcmRole":" ","admRole":"iaculis","lastUpdated":"12/7/2022","updateUser":"skindleysidess","comsId":"skindleysidess"},
{"userId":"30","firstName":"Bradan","lastName":"Corssen","email":"bcorssent@webs.com","location":"Uherský Brod","isActive":true,"zcmRole":" ","admRole":"cras","lastUpdated":"3/21/2023","updateUser":"bcorssent","comsId":"bcorssent"},
{"userId":"31","firstName":"Thorin","lastName":"Wonfor","email":"twonforu@nbcnews.com","location":"Žiežmariai","isActive":false,"zcmRole":" ","admRole":"elementum","lastUpdated":"6/21/2023","updateUser":"twonforu","comsId":"twonforu"},
{"userId":"32","firstName":"Wylie","lastName":"Bass","email":"wbassv@chron.com","location":"Cigadung","isActive":true,"zcmRole":" ","admRole":"interdum","lastUpdated":"5/1/2023","updateUser":"wbassv","comsId":"wbassv"},
{"userId":"33","firstName":"Gregoire","lastName":"Perotti","email":"gperottiw@4shared.com","location":"Saint-Nazaire","isActive":true,"zcmRole":" ","admRole":"amet","lastUpdated":"4/8/2023","updateUser":"gperottiw","comsId":"gperottiw"},
{"userId":"34","firstName":"Brian","lastName":"Large","email":"blargex@odnoklassniki.ru","location":"Phanom Sarakham","isActive":true,"zcmRole":" ","admRole":"sollicitudin","lastUpdated":"4/26/2023","updateUser":"blargex","comsId":"blargex"},
{"userId":"35","firstName":"Harry","lastName":"Stockbridge","email":"hstockbridgey@baidu.com","location":"Balong Wetan","isActive":true,"zcmRole":" ","admRole":"elit","lastUpdated":"1/23/2023","updateUser":"hstockbridgey","comsId":"hstockbridgey"},
{"userId":"36","firstName":"Kimmy","lastName":"Grinsted","email":"kgrinstedz@angelfire.com","location":"Ash Shafā","isActive":false,"zcmRole":" ","admRole":"mi","lastUpdated":"11/2/2022","updateUser":"kgrinstedz","comsId":"kgrinstedz"},
{"userId":"37","firstName":"Menard","lastName":"Tal","email":"mtal10@youku.com","location":"Dunyāpur","isActive":false,"zcmRole":" ","admRole":"in","lastUpdated":"10/25/2022","updateUser":"mtal10","comsId":"mtal10"},
{"userId":"38","firstName":"Shena","lastName":"Muschette","email":"smuschette11@cpanel.net","location":"Orléans","isActive":false,"zcmRole":" ","admRole":"duis","lastUpdated":"2/24/2023","updateUser":"smuschette11","comsId":"smuschette11"},
{"userId":"39","firstName":"Letisha","lastName":"O'Cahill","email":"locahill12@businesswire.com","location":"Lansing","isActive":false,"zcmRole":" ","admRole":"diam","lastUpdated":"5/24/2023","updateUser":"locahill12","comsId":"locahill12"},
{"userId":"40","firstName":"Merissa","lastName":"Domnin","email":"mdomnin13@nih.gov","location":"Langchuan","isActive":false,"zcmRole":"Architect","admRole":"primis","lastUpdated":"12/22/2022","updateUser":"mdomnin13","comsId":"mdomnin13"}]